{
  "assets": [
    {
      "browser_download_url": "https://github.com/BurntSushi/ripgrep/releases/download/13.0.0/ripgrep-13.0.0-arm-unknown-linux-gnueabihf.tar.gz",
      "content_type": "application/octet-stream",
      "created_at": "2021-06-12T12:31:57Z",
      "id": 38486868,
      "label": "",
      "name": "ripgrep-13.0.0-arm-unknown-linux-gnueabihf.tar.gz",
      "node_id": "MDEyOlJlbGVhc2VBc3NldDM4NDg2ODY4",
      "size": 1763861,
      "state": "uploaded",
      "updated_at": "2021-06-12T12:31:58Z",
      "uploader": {
        "avatar_url": "https://avatars.githubusercontent.com/in/15368?v=4",
        "events_url": "https://api.github.com/users/github-actions%5Bbot%5D/events{/privacy}",
        "followers_url": "https://api.github.com/users/github-actions%5Bbot%5D/followers",
        "following_url": "https://api.github.com/users/github-actions%5Bbot%5D/following{/other_user}",
        "gists_url": "https://api.github.com/users/github-actions%5Bbot%5D/gists{/gist_id}",
        "gravatar_id": "",
        "html_url": "https://github.com/apps/github-actions",
        "id": 41898282,
        "login": "github-actions[bot]",
        "node_id": "MDM6Qm90NDE4OTgyODI=",
        "organizations_url": "https://api.github.com/users/github-actions%5Bbot%5D/orgs",
        "received_events_url": "https://api.github.com/users/github-actions%5Bbot%5D/received_events",
        "repos_url": "https://api.github.com/users/github-actions%5Bbot%5D/repos",
        "site_admin": false,
        "starred_url": "https://api.github.com/users/github-actions%5Bbot%5D/starred{/owner}{/repo}",
        "subscriptions_url": "https://api.github.com/users/github-actions%5Bbot%5D/subscriptions",
        "type": "Bot",
        "url": "https://api.github.com/users/github-actions%5Bbot%5D"
      },
      "url": "https://api.github.com/repos/BurntSushi/ripgrep/releases/assets/38486868"
    },
    {
      "browser_download_url": "https://github.com/BurntSushi/ripgrep/releases/download/13.0.0/ripgrep-13.0.0-i686-pc-windows-msvc.zip",
      "content_type": "application/octet-stream",
      "created_at": "2021-06-12T12:32:47Z",
      "id": 38486879,
      "label": "",
      "name": "ripgrep-13.0.0-i686-pc-windows-msvc.zip",
      "node_id": "MDEyOlJlbGVhc2VBc3NldDM4NDg2ODc5",
      "size": 1591463,
      "state": "uploaded",
      "updated_at": "2021-06-12T12:32:48Z",
      "uploader": {
        "avatar_url": "https://avatars.githubusercontent.com/in/15368?v=4",
        "events_url": "https://api.github.com/users/github-actions%5Bbot%5D/events{/privacy}",
        "followers_url": "https://api.github.com/users/github-actions%5Bbot%5D/followers",
        "following_url": "https://api.github.com/users/github-actions%5Bbot%5D/following{/other_user}",
        "gists_url": "https://api.github.com/users/github-actions%5Bbot%5D/gists{/gist_id}",
        "gravatar_id": "",
        "html_url": "https://github.com/apps/github-actions",
        "id": 41898282,
        "login": "github-actions[bot]",
        "node_id": "MDM6Qm90NDE4OTgyODI=",
        "organizations_url": "https://api.github.com/users/github-actions%5Bbot%5D/orgs",
        "received_events_url": "https://api.github.com/users/github-actions%5Bbot%5D/received_events",
        "repos_url": "https://api.github.com/users/github-actions%5Bbot%5D/repos",
        "site_admin": false,
        "starred_url": "https://api.github.com/users/github-actions%5Bbot%5D/starred{/owner}{/repo}",
        "subscriptions_url": "https://api.github.com/users/github-actions%5Bbot%5D/subscriptions",
        "type": "Bot",
        "url": "https://api.github.com/users/github-actions%5Bbot%5D"
      },
      "url": "https://api.github.com/repos/BurntSushi/ripgrep/releases/assets/38486879"
    },
    {
      "browser_download_url": "https://github.com/BurntSushi/ripgrep/releases/download/13.0.0/ripgrep-13.0.0-x86_64-apple-darwin.tar.gz",
      "content_type": "application/octet-stream",
      "created_at": "2021-06-12T12:35:00Z",
      "id": 38486907,
      "label": "",
      "name": "ripgrep-13.0.0-x86_64-apple-darwin.tar.gz",
      "node_id": "MDEyOlJlbGVhc2VBc3NldDM4NDg2OTA3",
      "size": 1815615,
      "state": "uploaded",
      "updated_at": "2021-06-12T12:35:00Z",
      "uploader": {
        "avatar_url": "https://avatars.githubusercontent.com/in/15368?v=4",
        "events_url": "https://api.github.com/users/github-actions%5Bbot%5D/events{/privacy}",
        "followers_url": "https://api.github.com/users/github-actions%5Bbot%5D/followers",
        "following_url": "https://api.github.com/users/github-actions%5Bbot%5D/following{/other_user}",
        "gists_url": "https://api.github.com/users/github-actions%5Bbot%5D/gists{/gist_id}",
        "gravatar_id": "",
        "html_url": "https://github.com/apps/github-actions",
        "id": 41898282,
        "login": "github-actions[bot]",
        "node_id": "MDM6Qm90NDE4OTgyODI=",
        "organizations_url": "https://api.github.com/users/github-actions%5Bbot%5D/orgs",
        "received_events_url": "https://api.github.com/users/github-actions%5Bbot%5D/received_events",
        "repos_url": "https://api.github.com/users/github-actions%5Bbot%5D/repos",
        "site_admin": false,
        "starred_url": "https://api.github.com/users/github-actions%5Bbot%5D/starred{/owner}{/repo}",
        "subscriptions_url": "https://api.github.com/users/github-actions%5Bbot%5D/subscriptions",
        "type": "Bot",
        "url": "https://api.github.com/users/github-actions%5Bbot%5D"
      },
      "url": "https://api.github.com/repos/BurntSushi/ripgrep/releases/assets/38486907"
    },
    {
      "browser_download_url": "https://github.com/BurntSushi/ripgrep/releases/download/13.0.0/ripgrep-13.0.0-x86_64-pc-windows-gnu.zip",
      "content_type": "application/octet-stream",
      "created_at": "2021-06-12T12:33:25Z",
      "id": 38486889,
      "label": "",
      "name": "ripgrep-13.0.0-x86_64-pc-windows-gnu.zip",
      "node_id": "MDEyOlJlbGVhc2VBc3NldDM4NDg2ODg5",
      "size": 9811405,
      "state": "uploaded",
      "updated_at": "2021-06-12T12:33:26Z",
      "uploader": {
        "avatar_url": "https://avatars.githubusercontent.com/in/15368?v=4",
        "events_url": "https://api.github.com/users/github-actions%5Bbot%5D/events{/privacy}",
        "followers_url": "https://api.github.com/users/github-actions%5Bbot%5D/followers",
        "following_url": "https://api.github.com/users/github-actions%5Bbot%5D/following{/other_user}",
        "gists_url": "https://api.github.com/users/github-actions%5Bbot%5D/gists{/gist_id}",
        "gravatar_id": "",
        "html_url": "https://github.com/apps/github-actions",
        "id": 41898282,
        "login": "github-actions[bot]",
        "node_id": "MDM6Qm90NDE4OTgyODI=",
        "organizations_url": "https://api.github.com/users/github-actions%5Bbot%5D/orgs",
        "received_events_url": "https://api.github.com/users/github-actions%5Bbot%5D/received_events",
        "repos_url": "https://api.github.com/users/github-actions%5Bbot%5D/repos",
        "site_admin": false,
        "starred_url": "https://api.github.com/users/github-actions%5Bbot%5D/starred{/owner}{/repo}",
        "subscriptions_url": "https://api.github.com/users/github-actions%5Bbot%5D/subscriptions",
        "type": "Bot",
        "url": "https://api.github.com/users/github-actions%5Bbot%5D"
      },
      "url": "https://api.github.com/repos/BurntSushi/ripgrep/releases/assets/38486889"
    },
    {
      "browser_download_url": "https://github.com/BurntSushi/ripgrep/releases/download/13.0.0/ripgrep-13.0.0-x86_64-pc-windows-msvc.zip",
      "content_type": "application/octet-stream",
      "created_at": "2021-06-12T12:32:30Z",
      "id": 38486875,
      "label": "",
      "name": "ripgrep-13.0.0-x86_64-pc-windows-msvc.zip",
      "node_id": "MDEyOlJlbGVhc2VBc3NldDM4NDg2ODc1",
      "size": 1734357,
      "state": "uploaded",
      "updated_at": "2021-06-12T12:32:30Z",
      "uploader": {
        "avatar_url": "https://avatars.githubusercontent.com/in/15368?v=4",
        "events_url": "https://api.github.com/users/github-actions%5Bbot%5D/events{/privacy}",
        "followers_url": "https://api.github.com/users/github-actions%5Bbot%5D/followers",
        "following_url": "https://api.github.com/users/github-actions%5Bbot%5D/following{/other_user}",
        "gists_url": "https://api.github.com/users/github-actions%5Bbot%5D/gists{/gist_id}",
        "gravatar_id": "",
        "html_url": "https://github.com/apps/github-actions",
        "id": 41898282,
        "login": "github-actions[bot]",
        "node_id": "MDM6Qm90NDE4OTgyODI=",
        "organizations_url": "https://api.github.com/users/github-actions%5Bbot%5D/orgs",
        "received_events_url": "https://api.github.com/users/github-actions%5Bbot%5D/received_events",
        "repos_url": "https://api.github.com/users/github-actions%5Bbot%5D/repos",
        "site_admin": false,
        "starred_url": "https://api.github.com/users/github-actions%5Bbot%5D/starred{/owner}{/repo}",
        "subscriptions_url": "https://api.github.com/users/github-actions%5Bbot%5D/subscriptions",
        "type": "Bot",
        "url": "https://api.github.com/users/github-actions%5Bbot%5D"
      },
      "url": "https://api.github.com/repos/BurntSushi/ripgrep/releases/assets/38486875"
    },
    {
      "browser_download_url": "https://github.com/BurntSushi/ripgrep/releases/download/13.0.0/ripgrep-13.0.0-x86_64-unknown-linux-musl.tar.gz",
      "content_type": "application/octet-stream",
      "created_at": "2021-06-12T12:32:02Z",
      "id": 38486871,
      "label": "",
      "name": "ripgrep-13.0.0-x86_64-unknown-linux-musl.tar.gz",
      "node_id": "MDEyOlJlbGVhc2VBc3NldDM4NDg2ODcx",
      "size": 2109801,
      "state": "uploaded",
      "updated_at": "2021-06-12T12:32:03Z",
      "uploader": {
        "avatar_url": "https://avatars.githubusercontent.com/in/15368?v=4",
        "events_url": "https://api.github.com/users/github-actions%5Bbot%5D/events{/privacy}",
        "followers_url": "https://api.github.com/users/github-actions%5Bbot%5D/followers",
        "following_url": "https://api.github.com/users/github-actions%5Bbot%5D/following{/other_user}",
        "gists_url": "https://api.github.com/users/github-actions%5Bbot%5D/gists{/gist_id}",
        "gravatar_id": "",
        "html_url": "https://github.com/apps/github-actions",
        "id": 41898282,
        "login": "github-actions[bot]",
        "node_id": "MDM6Qm90NDE4OTgyODI=",
        "organizations_url": "https://api.github.com/users/github-actions%5Bbot%5D/orgs",
        "received_events_url": "https://api.github.com/users/github-actions%5Bbot%5D/received_events",
        "repos_url": "https://api.github.com/users/github-actions%5Bbot%5D/repos",
        "site_admin": false,
        "starred_url": "https://api.github.com/users/github-actions%5Bbot%5D/starred{/owner}{/repo}",
        "subscriptions_url": "https://api.github.com/users/github-actions%5Bbot%5D/subscriptions",
        "type": "Bot",
        "url": "https://api.github.com/users/github-actions%5Bbot%5D"
      },
      "url": "https://api.github.com/repos/BurntSushi/ripgrep/releases/assets/38486871"
    },
    {
      "browser_download_url": "https://github.com/BurntSushi/ripgrep/releases/download/13.0.0/ripgrep_13.0.0_amd64.deb",
      "content_type": "application/vnd.debian.binary-package",
      "created_at": "2021-06-12T17:36:20Z",
      "id": 38493219,
      "label": null,
      "name": "ripgrep_13.0.0_amd64.deb",
      "node_id": "MDEyOlJlbGVhc2VBc3NldDM4NDkzMjE5",
      "size": 1574096,
      "state": "uploaded",
      "updated_at": "2021-06-12T17:36:21Z",
      "uploader": {
        "avatar_url": "https://avatars.githubusercontent.com/u/456674?v=4",
        "events_url": "https://api.github.com/users/BurntSushi/events{/privacy}",
        "followers_url": "https://api.github.com/users/BurntSushi/followers",
        "following_url": "https://api.github.com/users/BurntSushi/following{/other_user}",
        "gists_url": "https://api.github.com/users/BurntSushi/gists{/gist_id}",
        "gravatar_id": "",
        "html_url": "https://github.com/BurntSushi",
        "id": 456674,
        "login": "BurntSushi",
        "node_id": "MDQ6VXNlcjQ1NjY3NA==",
        "organizations_url": "https://api.github.com/users/BurntSushi/orgs",
        "received_events_url": "https://api.github.com/users/BurntSushi/received_events",
        "repos_url": "https://api.github.com/users/BurntSushi/repos",
        "site_admin": false,
        "starred_url": "https://api.github.com/users/BurntSushi/starred{/owner}{/repo}",
        "subscriptions_url": "https://api.github.com/users/BurntSushi/subscriptions",
        "type": "User",
        "url": "https://api.github.com/users/BurntSushi"
      },
      "url": "https://api.github.com/repos/BurntSushi/ripgrep/releases/assets/38493219"
    }
  ],
  "assets_url": "https://api.github.com/repos/BurntSushi/ripgrep/releases/44518686/assets",
  "author": {
    "avatar_url": "https://avatars.githubusercontent.com/in/15368?v=4",
    "events_url": "https://api.github.com/users/github-actions%5Bbot%5D/events{/privacy}",
    "followers_url": "https://api.github.com/users/github-actions%5Bbot%5D/followers",
    "following_url": "https://api.github.com/users/github-actions%5Bbot%5D/following{/other_user}",
    "gists_url": "https://api.github.com/users/github-actions%5Bbot%5D/gists{/gist_id}",
    "gravatar_id": "",
    "html_url": "https://github.com/apps/github-actions",
    "id": 41898282,
    "login": "github-actions[bot]",
    "node_id": "MDM6Qm90NDE4OTgyODI=",
    "organizations_url": "https://api.github.com/users/github-actions%5Bbot%5D/orgs",
    "received_events_url": "https://api.github.com/users/github-actions%5Bbot%5D/received_events",
    "repos_url": "https://api.github.com/users/github-actions%5Bbot%5D/repos",
    "site_admin": false,
    "starred_url": "https://api.github.com/users/github-actions%5Bbot%5D/starred{/owner}{/repo}",
    "subscriptions_url": "https://api.github.com/users/github-actions%5Bbot%5D/subscriptions",
    "type": "Bot",
    "url": "https://api.github.com/users/github-actions%5Bbot%5D"
  },
  "created_at": "2021-06-12T12:12:24Z",
  "draft": false,
  "html_url": "https://github.com/BurntSushi/ripgrep/releases/tag/13.0.0",
  "id": 44518686,
  "name": "13.0.0",
  "node_id": "MDc6UmVsZWFzZTQ0NTE4Njg2",
  "prerelease": false,
  "published_at": "2021-06-12T12:27:16Z",
  "tag_name": "13.0.0",
  "tarball_url": "https://api.github.com/repos/BurntSushi/ripgrep/tarball/13.0.0",
  "target_commitish": "af6b6c543b224d348a8876f0c06245d9ea7929c5",
  "upload_url": "https://uploads.github.com/repos/BurntSushi/ripgrep/releases/44518686/assets{?name,label}",
  "url": "https://api.github.com/repos/BurntSushi/ripgrep/releases/44518686",
  "zipball_url": "https://api.github.com/repos/BurntSushi/ripgrep/zipball/13.0.0"
}
